README.md
setup.py
aquachain/__init__.py
aquachain/aquakeys.py
aquachain/aquatool.py
aquachain/bip44.py
aquachain/utils44.py
aquachain.py.egg-info/PKG-INFO
aquachain.py.egg-info/SOURCES.txt
aquachain.py.egg-info/dependency_links.txt
aquachain.py.egg-info/requires.txt
aquachain.py.egg-info/top_level.txt
aquachain/crypto/__init__.py
aquachain/crypto/ecdsa.py
aquachain/crypto/ecdsa_base.py
aquachain/crypto/ecdsa_openssl.py
aquachain/crypto/ecdsa_python.py
aquachain/crypto/openssl.py