Metadata-Version: 1.1
Name: aquachain.py
Version: 0.0.7
Summary: Aquachain for Python 3.6.5
Home-page: https://github.com/aquachain/aquachain.py
Author: Aquachain Authors
Author-email: aquachain@riseup.net
License: GPL
Platform: UNKNOWN
Classifier: Development Status :: 2 - Pre-Alpha
Classifier: License :: Free for non-commercial use
Classifier: License :: OSI Approved :: GNU General Public License (GPL)
